image_processor/__init__.py
image_processor/processing.py
my_image_Processor_DioPro-0.1.dist-info/METADATA
my_image_Processor_DioPro-0.1.dist-info/WHEEL
my_image_Processor_DioPro-0.1.dist-info/top_level.txt
my_image_Processor_DioPro-0.1.dist-info/RECORD
